pdfbook/__init__.py
pdfbook/cmd.py
pdfbook/i18n.py
pdfbook/locale/de/LC_MESSAGES/pdfbook.mo
pdfbook-0.1.0.dist-info/LICENSE-AGPLv3.txt
pdfbook-0.1.0.dist-info/METADATA
pdfbook-0.1.0.dist-info/WHEEL
pdfbook-0.1.0.dist-info/entry_points.txt
pdfbook-0.1.0.dist-info/top_level.txt
pdfbook-0.1.0.dist-info/RECORD
