Metadata-Version: 2.1
Name: pdfbook
Version: 0.1.0
Summary: Rearrange pages in PDFs for printing books
Home-page: https://pdfbook.readthedocs.io/
Author: Hartmut Goebel
Author-email: h.goebel@crazy-compilers.com
License: AGPLv3+
Download-URL: https://pypi.org/project/pdfbook/
Keywords: pdf,book
Platform: UNKNOWN
Classifier: Development Status :: 4 - Beta
Classifier: Environment :: Console
Classifier: Intended Audience :: End Users/Desktop
Classifier: License :: OSI Approved :: GNU Affero General Public License v3 or later (AGPLv3+)
Classifier: Natural Language :: English
Classifier: Operating System :: OS Independent
Classifier: Programming Language :: Python
Classifier: Programming Language :: Python :: 3
Classifier: Programming Language :: Python :: 3.6
Classifier: Programming Language :: Python :: 3.7
Classifier: Programming Language :: Python :: 3.8
Classifier: Programming Language :: Python :: 3.9
Classifier: Programming Language :: Python :: 3.10
Classifier: Programming Language :: Python :: 3.11
Classifier: Topic :: Printing
Classifier: Topic :: Utilities
Requires-Dist: PyPDF2 (<3,>=2.1.1)
